azure/__init__.py
azure/cli/__init__.py
azure/cli/command_modules/__init__.py
azure/cli/command_modules/maps/__init__.py
azure/cli/command_modules/maps/_client_factory.py
azure/cli/command_modules/maps/_help.py
azure/cli/command_modules/maps/_params.py
azure/cli/command_modules/maps/commands.py
azure/cli/command_modules/maps/custom.py
azure_cli_maps-0.3.5.dist-info/METADATA
azure_cli_maps-0.3.5.dist-info/WHEEL
azure_cli_maps-0.3.5.dist-info/top_level.txt
azure_cli_maps-0.3.5.dist-info/RECORD
